MPv11/ram.v
module ram (Address, WriteData, ReadData, Clk, WE, RE);

/////////////////////////////////////////
// Inputs and Outputs
/////////////////////////////////////////
  input [7:0] Address;
  input [15:0] WriteData;
  output [15:0] ReadData;
  input Clk, WE, RE;

/////////////////////////////////////////
// Wires
/////////////////////////////////////////
  // For debugging!
  wire [15:0] addr_9, addr_10, addr_11;

/////////////////////////////////////////
// Memory Array
/////////////////////////////////////////
  reg [15:0] Mem [0:255];

/////////////////////////////////////////
// Logic for Module
/////////////////////////////////////////
  assign ReadData = RE ? Mem[Address] : 16'b0;

  always @(posedge Clk) begin
    if (WE)
      Mem[Address] <= WriteData;
  end

  // Debugging
  assign addr_9 = Mem[9];
  assign addr_10 = Mem[10];
  assign addr_11 = Mem[11];

endmodule

MPv11/alu.v
module alu (reg_a_data, reg_b_data, immediate, opcode, addressing_mode, result, cmp_result);

/////////////////////////////////////////
// Inputs and Outputs
/////////////////////////////////////////
input [15:0] reg_a_data, reg_b_data;
input [3:0] opcode;
input addressing_mode;
input [4:0] immediate;

output [15:0] result;
output [3:0] cmp_result;

/////////////////////////////////////////
// Wires
/////////////////////////////////////////
wire [15:0] op1, op2;
wire [15:0] result_add, result_sub, result_and, result_eor, result_orr, result_lsl, result_lsr;
reg [15:0] result;
wire result_gt, result_lt, result_eq, result_ne;

/////////////////////////////////////////
// Registers
/////////////////////////////////////////
// None

/////////////////////////////////////////
// Local Parameters
/////////////////////////////////////////
localparam
    MOV = 4'b0100,
    MVN = 4'b1011, 
    AND = 4'b1000,
    ORR = 4'b1001,
    EOR = 4'b1010,
    LSL = 4'b1100,
    LSR = 4'b1101,
    ADD = 4'b0010,
    SUB = 4'b0011;

/////////////////////////////////////////
// Logic for Module
/////////////////////////////////////////

assign op1 = reg_a_data;
assign op2 = addressing_mode ? reg_b_data : {11'b0, immediate};

always @(*)
    case (opcode)
        ADD: result = result_add;
        SUB: result = result_sub;
        AND: result = result_and;
        ORR: result = result_orr;
        EOR: result = result_eor;
        LSL: result = result_lsl;
        LSR: result = result_lsr;
        MOV: result = op2;
        MVN: result = ~op2;
        default: result = 16'bx;
    endcase

assign result_add = op1 + op2;
assign result_sub = op1 - op2;
assign result_and = op1 & op2;
assign result_orr = op1 | op2;
assign result_eor = op1 ^ op2;
assign result_lsl = op1 << op2;
assign result_lsr = op1 >> op2;

// Compare results
assign result_gt = op1 > op2;
assign result_lt = op1 < op2;
assign result_ne = result_gt || result_lt;
assign result_eq = !result_ne;
assign cmp_result = {result_gt, result_lt, result_ne, result_eq};

endmodule

MPv11/regfile.v
module regfile (clk, ra, rb, rc, write_enable, write_data, read_data_a, read_data_b);

/////////////////////////////////////////
// Inputs and Outputs
/////////////////////////////////////////
input clk;
input [2:0] ra, rb, rc;
input write_enable;
input [15:0] write_data;

output [15:0] read_data_a, read_data_b;

/////////////////////////////////////////
// Wires
/////////////////////////////////////////
reg [15:0] read_data_a, read_data_b; // These are wires
wire wen0, wen1, wen2, wen3, wen4, wen5, wen6, wen7;

/////////////////////////////////////////
// Registers
/////////////////////////////////////////
reg [15:0] r0, r1, r2, r3, r4, r5, r6, r7;

/////////////////////////////////////////
// Logic for Module
/////////////////////////////////////////
// Read Port A Multiplexor
always @(*) begin
    case (ra)
    3'd0 : read_data_a <= r0;
    3'd1 : read_data_a <= r1;
    3'd2 : read_data_a <= r2;
    3'd3 : read_data_a <= r3;
    3'd4 : read_data_a <= r4;
    3'd5 : read_data_a <= r5;
    3'd6 : read_data_a <= r6;
    3'd7 : read_data_a <= r7;
    default: read_data_a <= 16'bx;
    endcase
end

// Read Port B Multiplexor
always @(*) begin
    case (rb)
    3'd0 : read_data_b <= r0;
    3'd1 : read_data_b <= r1;
    3'd2 : read_data_b <= r2;
    3'd3 : read_data_b <= r3;
    3'd4 : read_data_b <= r4;
    3'd5 : read_data_b <= r5;
    3'd6 : read_data_b <= r6;
    3'd7 : read_data_b <= r7;
    default: read_data_b <= 16'bx;
    endcase
end

assign wen0 = write_enable && (rc == 3'd0);
assign wen1 = write_enable && (rc == 3'd1);
assign wen2 = write_enable && (rc == 3'd2);
assign wen3 = write_enable && (rc == 3'd3);
assign wen4 = write_enable && (rc == 3'd4);
assign wen5 = write_enable && (rc == 3'd5);
assign wen6 = write_enable && (rc == 3'd6);
assign wen7 = write_enable && (rc == 3'd7);

always @(posedge clk)
    if (wen0)
        r0 <= write_data;

always @(posedge clk)
    if (wen1)
        r1 <= write_data;

always @(posedge clk)
    if (wen2)
        r2 <= write_data;

always @(posedge clk)
    if (wen3)
        r3 <= write_data;

always @(posedge clk)
    if (wen4)
        r4 <= write_data;

always @(posedge clk)
    if (wen5)
        r5 <= write_data;

always @(posedge clk)
    if (wen6)
        r6 <= write_data;

always @(posedge clk)
    if (wen7)
        r7 <= write_data;

endmodule

MPv11/control_unit.v
module control_unit (nreset, clk, ram_read, ram_write, ram_address, instruction_data, ra, rb, rc, reg_write, load_e, immediate_e, opcode_e, addressing_mode_e, cmp_result);

/////////////////////////////////////////
// Inputs and Outputs
/////////////////////////////////////////
input nreset, clk;

output load_e, addressing_mode_e;
output [4:0] immediate_e;
output [3:0] opcode_e;
input [3:0] cmp_result;
output ram_read, ram_write, reg_write;
output [7:0] ram_address;
output [2:0] ra, rb, rc;
input [15:0] instruction_data;

/////////////////////////////////////////
// Local Parameters
/////////////////////////////////////////
localparam 
    FETCH  = 2'b00,
    BUBBLE = 2'b01,
    HALTED = 2'b10;

localparam 
    MOV = 4'b0100,
    MVN = 4'b1011, 
    BAL = 4'b0110,
    BCOND = 4'b0111,
    CMP = 4'b0101,
    AND = 4'b1000,
    ORR = 4'b1001,
    EOR = 4'b1010,
    LSL = 4'b1100,
    LSR = 4'b1101,
    ADD = 4'b0010,
    SUB = 4'b0011,
    STR  = 4'b0001,
    LDR  = 4'b0000,
    HALT = 4'b1111;

/////////////////////////////////////////
// Wires
/////////////////////////////////////////
wire alu_op_d;
wire fetch;
wire execute_cmp;
wire [3:0] opcode_d;
reg flush;

// Program Counter Logic
reg [7:0] next_pc_f;
wire [7:0] inc_pc_f;

// State logic
reg [1:0] next_state;

/////////////////////////////////////////
// Registers
/////////////////////////////////////////
reg [3:0] status; // Status Register
reg [15:0] cir_d; // Current Instruction Register in decode
reg [15:0] cir_e; // Current Instruction Register in execute
reg [7:0] pc_f; // Program Counter
reg [1:0] state; // Halted. Fetch, Bubble
reg alu_op_e;
reg execute_store_e, execute_load_e, do_halt_e, decode, execute;

/////////////////////////////////////////
// Logic for Module
/////////////////////////////////////////

// Control for the ALU
assign opcode_d = cir_d[15:12];
assign opcode_e = cir_e[15:12];
assign addressing_mode_e = cir_e[11];
assign immediate_e = cir_e[10:6];
assign load_e = execute_load_e;
assign alu_op_d = (
        (opcode_d == MOV) || 
        (opcode_d == MVN) || 
        (opcode_d == AND) || 
        (opcode_d == ORR) || 
        (opcode_d == EOR) || 
        (opcode_d == LSL) || 
        (opcode_d == LSR) || 
        (opcode_d == ADD) || 
        (opcode_d == SUB));

// Control for the RAM
assign ram_read = fetch || (execute && execute_load_e);
assign ram_write = execute && execute_store_e;
assign reg_write = execute && (execute_load_e || alu_op_e);


// Control for the Register File
assign ra = execute_store_e ? cir_e[2:0] : cir_e[5:3]; // Store instruction or ALU op
assign rb = cir_e[8:6];
assign rc = cir_e[2:0]; // Write port

// Address Mux
assign ram_address = fetch ? pc_f : cir_e[10:3];

// Decoder logic
always @(posedge clk or negedge nreset)
    if (!nreset) begin
        execute_store_e <= 1'b0;
        execute_load_e <= 1'b0;
        do_halt_e <= 1'b0;
        alu_op_e <= 1'b0;
    end
    else if (decode) begin
        execute_store_e <= (opcode_d == STR);
        execute_load_e <= (opcode_d == LDR);
        do_halt_e <= (opcode_d == HALT);
        alu_op_e <= alu_op_d;
    end

// Program Counter Logic
assign inc_pc_f = pc_f + 8'd1;

always @(*)
    if (execute && (opcode_e == BAL)) begin // Branch Always
        next_pc_f = cir_e[7:0];
        flush = 1'b1;
    end else if (execute && (opcode_e == BCOND))
        // More to do here
        if ((cir_e[11:10] == 2'b00) && status[0]) begin
            next_pc_f = cir_e[7:0];
            flush = 1'b1;
        end else if ((cir_e[11:10] == 2'b11) && status[1]) begin
            next_pc_f = cir_e[7:0];
            flush = 1'b1;
        end else if ((cir_e[11:10] == 2'b01) && status[3]) begin
            next_pc_f = cir_e[7:0];
            flush = 1'b1;
        end else if ((cir_e[11:10] == 2'b10) && status[2]) begin
            next_pc_f = cir_e[7:0];
            flush = 1'b1;
        end else begin
            next_pc_f = inc_pc_f;
            flush = 1'b0;
        end
    else begin
        next_pc_f = inc_pc_f;
        flush = 1'b0;
    end

always @(posedge clk or negedge nreset)
    if (!nreset)
        pc_f <= 8'd0;
    else if (fetch)
        pc_f <= next_pc_f;

// cir_d Logic
assign fetch = (state == FETCH) ? 1'b1 : 1'b0;
always @(posedge clk)
    if (fetch) begin
        cir_d <= instruction_data;
    end

always @(posedge clk)
    if (decode) begin
        cir_e <= cir_d;
    end

always @(posedge clk or negedge nreset)
    if (!nreset) begin
        decode <= 1'b0;
        execute <= 1'b0;
    end 
    else begin
        decode <= fetch && !flush && !do_halt_e;
        execute <= decode && !flush && !do_halt_e;
    end

// State Logic
always @(posedge clk or negedge nreset)
    if (!nreset)
        state <= BUBBLE;
    else
        state <= next_state;

always @(*)
    if (do_halt_e || (state == HALTED))
        next_state = HALTED;
    else if (!flush && decode && ((opcode_d == LDR) || (opcode_d == STR)))
        next_state = BUBBLE;
    else
        next_state = FETCH;

// Status Register Logic
assign execute_cmp = execute && (opcode_e == CMP);
always @(posedge clk or negedge nreset)
    if (!nreset)
        status <= 4'b0000;
    else if (execute_cmp)
        status <= cmp_result;

endmodule

MPv11/processor.v
module processor (clk, nreset, address_bus, rdata_bus, wdata_bus, control_bus);

/////////////////////////////////////////
// Inputs and Outputs
/////////////////////////////////////////
input clk, nreset;
output [7:0] address_bus;
output [1:0] control_bus;
output [15:0] wdata_bus;
input [15:0] rdata_bus;

/////////////////////////////////////////
// Wires
/////////////////////////////////////////
wire ram_read, ram_write, reg_write;
wire [2:0] ra, rb, rc;
wire load, addressing_mode;
wire [4:0] immediate;
wire [3:0] opcode;
wire [15:0] reg_a_data, reg_b_data;
wire [15:0] reg_write_data, alu_result;
wire [3:0] cmp_result;

/////////////////////////////////////////
// Logic for Module
/////////////////////////////////////////
assign control_bus = {ram_read, ram_write};
assign reg_write_data = load ? rdata_bus : alu_result;
assign wdata_bus = reg_a_data;

/////////////////////////////////////////
// Instances
/////////////////////////////////////////
control_unit cu (
    .nreset (nreset), 
    .clk    (clk), 
    .ram_read         (ram_read), 
    .ram_address      (address_bus), 
    .instruction_data (rdata_bus),
    .ra (ra),
    .rb (rb),
    .rc (rc),
    .ram_write        (ram_write),
    .reg_write        (reg_write),

    //  For ALU Control
    .load_e            (load),
    .immediate_e       (immediate), 
    .opcode_e          (opcode), 
    .addressing_mode_e (addressing_mode),
    .cmp_result        (cmp_result)
    );

regfile ureg (
    .clk (clk), 
    .ra (ra), 
    .rb (rb), 
    .rc (rc), 
    .write_enable (reg_write), 
    .write_data   (reg_write_data), 
    .read_data_a  (reg_a_data), 
    .read_data_b  (reg_b_data)
);

alu ualu (
    .reg_a_data (reg_a_data), 
    .reg_b_data (reg_b_data), 
    .immediate  (immediate), 
    .opcode     (opcode), 
    .addressing_mode (addressing_mode),
    .result (alu_result),
    .cmp_result(cmp_result)
    );

endmodule

MPv11/processor_tb.v
`timescale 1ns/1ps 

module processor_tb;

reg clk = 0;
reg nreset;

always #1 clk = !clk;

initial begin
    $readmemh("C:\\Users\\nhlo\\Documents\\GitHub\\PythonCompiler\\main\\memory.txt", u_ram.Mem,0,255);
    $dumpfile("iexec.vcd");
    $dumpvars(0,processor_tb);
    #1
    nreset = 0;
    #1
    nreset = 1;
    #10000
    $finish;
end

wire [7:0] addr;
wire [15:0] wdata;
wire [15:0] rdata;
wire we;
wire re;
wire [1:0] control_bus;

processor dut (
    .clk (clk), 
    .nreset (nreset), 
    .address_bus (addr), 
    .rdata_bus (rdata), 
    .wdata_bus (wdata), 
    .control_bus (control_bus)
    );

assign we = control_bus[0];
assign re = control_bus[1];

ram u_ram (
    .Address (addr), 
    .WriteData (wdata), 
    .ReadData (rdata), 
    .Clk (clk), 
    .WE (we), 
    .RE (re)
    );

endmodule

main/iexec.vcd
$date
	Tue May 07 13:21:05 2024
$end
$version
	Icarus Verilog
$end
$timescale
	1ps
$end
$scope module processor_tb $end
$var wire 1 ! we $end
$var wire 16 " wdata [15:0] $end
$var wire 1 # re $end
$var wire 16 $ rdata [15:0] $end
$var wire 2 % control_bus [1:0] $end
$var wire 8 & addr [7:0] $end
$var reg 1 ' clk $end
$var reg 1 ( nreset $end
$scope module dut $end
$var wire 1 ' clk $end
$var wire 1 ( nreset $end
$var wire 16 ) wdata_bus [15:0] $end
$var wire 16 * reg_write_data [15:0] $end
$var wire 1 + reg_write $end
$var wire 16 , reg_b_data [15:0] $end
$var wire 16 - reg_a_data [15:0] $end
$var wire 16 . rdata_bus [15:0] $end
$var wire 3 / rc [2:0] $end
$var wire 3 0 rb [2:0] $end
$var wire 1 1 ram_write $end
$var wire 1 2 ram_read $end
$var wire 3 3 ra [2:0] $end
$var wire 4 4 opcode [3:0] $end
$var wire 1 5 load $end
$var wire 5 6 immediate [4:0] $end
$var wire 2 7 control_bus [1:0] $end
$var wire 4 8 cmp_result [3:0] $end
$var wire 16 9 alu_result [15:0] $end
$var wire 1 : addressing_mode $end
$var wire 8 ; address_bus [7:0] $end
$scope module cu $end
$var wire 1 < alu_op_d $end
$var wire 1 ' clk $end
$var wire 1 = execute_cmp $end
$var wire 1 5 load_e $end
$var wire 1 ( nreset $end
$var wire 1 2 ram_read $end
$var wire 1 1 ram_write $end
$var wire 1 + reg_write $end
$var wire 3 > rc [2:0] $end
$var wire 3 ? rb [2:0] $end
$var wire 8 @ ram_address [7:0] $end
$var wire 3 A ra [2:0] $end
$var wire 4 B opcode_e [3:0] $end
$var wire 4 C opcode_d [3:0] $end
$var wire 16 D instruction_data [15:0] $end
$var wire 8 E inc_pc_f [7:0] $end
$var wire 5 F immediate_e [4:0] $end
$var wire 1 G fetch $end
$var wire 4 H cmp_result [3:0] $end
$var wire 1 : addressing_mode_e $end
$var parameter 4 I ADD $end
$var parameter 4 J AND $end
$var parameter 4 K BAL $end
$var parameter 4 L BCOND $end
$var parameter 2 M BUBBLE $end
$var parameter 4 N CMP $end
$var parameter 4 O EOR $end
$var parameter 2 P FETCH $end
$var parameter 4 Q HALT $end
$var parameter 2 R HALTED $end
$var parameter 4 S LDR $end
$var parameter 4 T LSL $end
$var parameter 4 U LSR $end
$var parameter 4 V MOV $end
$var parameter 4 W MVN $end
$var parameter 4 X ORR $end
$var parameter 4 Y STR $end
$var parameter 4 Z SUB $end
$var reg 1 [ alu_op_e $end
$var reg 16 \ cir_d [15:0] $end
$var reg 16 ] cir_e [15:0] $end
$var reg 1 ^ decode $end
$var reg 1 _ do_halt_e $end
$var reg 1 ` execute $end
$var reg 1 a execute_load_e $end
$var reg 1 b execute_store_e $end
$var reg 1 c flush $end
$var reg 8 d next_pc_f [7:0] $end
$var reg 2 e next_state [1:0] $end
$var reg 8 f pc_f [7:0] $end
$var reg 2 g state [1:0] $end
$var reg 4 h status [3:0] $end
$upscope $end
$scope module ualu $end
$var wire 1 : addressing_mode $end
$var wire 5 i immediate [4:0] $end
$var wire 16 j op1 [15:0] $end
$var wire 4 k opcode [3:0] $end
$var wire 16 l result_and [15:0] $end
$var wire 16 m result_eor [15:0] $end
$var wire 1 n result_ne $end
$var wire 16 o result_orr [15:0] $end
$var wire 16 p result_sub [15:0] $end
$var wire 1 q result_lt $end
$var wire 16 r result_lsr [15:0] $end
$var wire 16 s result_lsl [15:0] $end
$var wire 1 t result_gt $end
$var wire 1 u result_eq $end
$var wire 16 v result_add [15:0] $end
$var wire 16 w reg_b_data [15:0] $end
$var wire 16 x reg_a_data [15:0] $end
$var wire 16 y op2 [15:0] $end
$var wire 4 z cmp_result [3:0] $end
$var parameter 4 { ADD $end
$var parameter 4 | AND $end
$var parameter 4 } EOR $end
$var parameter 4 ~ LSL $end
$var parameter 4 !" LSR $end
$var parameter 4 "" MOV $end
$var parameter 4 #" MVN $end
$var parameter 4 $" ORR $end
$var parameter 4 %" SUB $end
$var reg 16 &" result [15:0] $end
$upscope $end
$scope module ureg $end
$var wire 1 ' clk $end
$var wire 3 '" ra [2:0] $end
$var wire 3 (" rb [2:0] $end
$var wire 3 )" rc [2:0] $end
$var wire 1 *" wen0 $end
$var wire 1 +" wen1 $end
$var wire 1 ," wen2 $end
$var wire 1 -" wen3 $end
$var wire 1 ." wen4 $end
$var wire 1 /" wen5 $end
$var wire 1 0" wen6 $end
$var wire 1 1" wen7 $end
$var wire 16 2" write_data [15:0] $end
$var wire 1 + write_enable $end
$var reg 16 3" r0 [15:0] $end
$var reg 16 4" r1 [15:0] $end
$var reg 16 5" r2 [15:0] $end
$var reg 16 6" r3 [15:0] $end
$var reg 16 7" r4 [15:0] $end
$var reg 16 8" r5 [15:0] $end
$var reg 16 9" r6 [15:0] $end
$var reg 16 :" r7 [15:0] $end
$var reg 16 ;" read_data_a [15:0] $end
$var reg 16 <" read_data_b [15:0] $end
$upscope $end
$upscope $end
$scope module u_ram $end
$var wire 8 =" Address [7:0] $end
$var wire 1 ' Clk $end
$var wire 1 # RE $end
$var wire 1 ! WE $end
$var wire 16 >" WriteData [15:0] $end
$var wire 16 ?" addr_10 [15:0] $end
$var wire 16 @" addr_11 [15:0] $end
$var wire 16 A" addr_9 [15:0] $end
$var wire 16 B" ReadData [15:0] $end
$upscope $end
$upscope $end
$enddefinitions $end
$comment Show the parameter values. $end
$dumpall
b11 %"
b1001 $"
b1011 #"
b100 ""
b1101 !"
b1100 ~
b1010 }
b1000 |
b10 {
b11 Z
b1 Y
b1001 X
b1011 W
b100 V
b1101 U
b1100 T
b0 S
b10 R
b1111 Q
b0 P
b1010 O
b101 N
b1 M
b111 L
b110 K
b1000 J
b10 I
$end
#0
$dumpvars
bx B"
b100001010 A"
b1000100000000 @"
b10100010001000 ?"
bx >"
bx ="
bx <"
bx ;"
bx :"
bx 9"
bx 8"
bx 7"
bx 6"
bx 5"
bx 4"
bx 3"
bx 2"
x1"
x0"
x/"
x."
x-"
x,"
x+"
x*"
bx )"
bx ("
bx '"
bx &"
bx z
bx y
bx x
bx w
bx v
xu
xt
bx s
bx r
xq
bx p
bx o
xn
bx m
bx l
bx k
bx j
bx i
bx h
bx g
bx f
bx e
bx d
xc
xb
xa
x`
x_
x^
bx ]
bx \
x[
bx H
xG
bx F
bx E
bx D
bx C
bx B
bx A
bx @
bx ?
bx >
x=
x<
bx ;
x:
bx 9
bx 8
bx 7
bx 6
x5
bx 4
bx 3
x2
x1
bx 0
bx /
bx .
bx -
bx ,
x+
bx *
bx )
x(
0'
bx &
bx %
bx $
x#
bx "
x!
$end
#1000
b0 $
b0 .
b0 D
b0 B"
0#
0*"
0+"
0,"
0-"
0."
0/"
00"
01"
0!
02
0=
0+
b0 %
b0 7
01
b0 e
0G
0c
b1 d
0[
0_
05
0a
0b
b1 E
b0 f
0`
0^
b1 g
b0 h
0(
1'
#2000
1(
0'
#3000
b100000000000000 $
b100000000000000 .
b100000000000000 D
b100000000000000 B"
1#
b0 &
b0 ;
b0 @
b0 ="
b10 %
b10 7
12
1G
b0 g
1'
#4000
0'
#5000
1<
b1000100000000 $
b1000100000000 .
b1000100000000 D
b1000100000000 B"
b1 &
b1 ;
b1 @
b1 ="
b10 d
b100 C
b10 E
b1 f
1^
b100000000000000 \
1'
#6000
0'
#7000
0<
b0 *
b0 2"
b0 l
b100000000000000 $
b100000000000000 .
b100000000000000 D
b100000000000000 B"
b0 9
b0 &"
b0 y
b0 3
b0 A
b0 '"
1*"
b1 e
1+
b10 &
b10 ;
b10 @
b10 ="
b11 d
b100 4
b100 B
b100 k
0:
b0 6
b0 F
b0 i
b0 0
b0 ?
b0 ("
b0 /
b0 >
b0 )"
b1 C
1`
b11 E
b10 f
1[
b100000000000000 ]
b1000100000000 \
1'
#8000
0'
#9000
b100 m
0u
1n
bx ,
bx w
bx <"
b100 v
b1111111111111100 p
0t
b110 8
b110 H
b110 z
1q
b0 j
b0 "
b0 )
b0 >"
b0 -
b0 x
b0 ;"
1<
0*"
0#
bx *
bx 2"
b100 o
b0 l
0+
1!
b0 $
b0 .
b0 D
b0 B"
02
bx 9
bx &"
b0 s
b0 r
b100 y
b1 %
b1 7
11
b100000 &
b100000 ;
b100000 @
b100000 ="
b0 e
0G
b100 C
b100 d
b1 4
b1 B
b1 k
b100 6
b100 F
b100 i
b100 0
b100 ?
b100 ("
0[
1b
b100 E
b11 f
b1 g
b100000000000000 \
b1000100000000 ]
b0 3"
1'
#10000
0'
#11000
b0 ,
b0 w
b0 <"
b1000100001000 $
b1000100001000 .
b1000100001000 D
b1000100001000 B"
1#
1*"
b0 *
b0 2"
1u
0n
b0 m
b0 o
12
1+
0!
b0 9
b0 &"
b0 v
b0 p
b1 8
b1 H
b1 z
0q
b0 y
b11 &
b11 ;
b11 @
b11 ="
1G
b10 %
b10 7
01
b100 4
b100 B
b100 k
b0 6
b0 F
b0 i
b0 0
b0 ?
b0 ("
b0 g
0^
1[
0b
b100000000000000 ]
1'
#12000
0'
#13000
0<
b100001000 $
b100001000 .
b100001000 D
b100001000 B"
0*"
b100 &
b100 ;
b100 @
b100 ="
b101 d
0+
b1 e
b1 C
b101 E
b100 f
0`
1^
b1000100001000 \
1'
#14000
0'
#15000
bx ,
bx w
bx <"
0#
bx *
bx 2"
0u
1n
b100 m
b100 o
02
b0 $
b0 .
b0 D
b0 B"
1!
bx 9
bx &"
b100 v
b1111111111111100 p
b110 8
b110 H
b110 z
1q
b100 y
0G
b100001 &
b100001 ;
b100001 @
b100001 ="
b1 %
b1 7
11
b110 d
b1 4
b1 B
b1 k
b100 6
b100 F
b100 i
b100 0
b100 ?
b100 ("
b0 C
b1 g
1`
b110 E
b101 f
0[
1b
b1000100001000 ]
b100001000 \
1'
#16000
0'
#17000
b0x00 l
bx1xx o
bx m
xu
xn
bx v
bx p
bx0000 s
b0xxxxxxxxxxxx r
xt
bx 8
bx H
bx z
xq
bx j
bx "
bx )
bx >"
bx -
bx x
bx ;"
1*"
1#
1+
12
0!
b0 *
b0 2"
b1 3
b1 A
b1 '"
b10 %
b10 7
01
b0 e
b0 4
b0 B
b0 k
15
1a
0b
0^
b100001000 ]
1'
#18000
0'
#19000
b101011111000000 *
b101011111000000 2"
b101011111000000 $
b101011111000000 .
b101011111000000 D
b101011111000000 B"
b101 &
b101 ;
b101 @
b101 ="
0*"
1G
0+
b0 g
0`
1'
#20000
0'
#21000
b111100000001000 *
b111100000001000 2"
b111100000001000 $
b111100000001000 .
b111100000001000 D
b111100000001000 B"
b110 &
b110 ;
b110 @
b110 ="
b111 d
b101 C
b111 E
b110 f
1^
b101011111000000 \
1'
#22000
0'
#23000
b11111 m
0u
1n
b11111 v
b1111111111100001 p
0t
b110 8
b110 H
b110 z
1q
b0 j
b0 "
b0 )
b0 >"
b0 -
b0 x
b0 ;"
b11111 o
b0 l
b110000000010000 $
b110000000010000 .
b110000000010000 D
b110000000010000 B"
b0 s
b0 r
b11111 y
b0 3
b0 A
b0 '"
1=
b111 &
b111 ;
b111 @
b111 ="
bx *
bx 2"
b1000 d
b101 4
b101 B
b101 k
b11111 6
b11111 F
b11111 i
b111 0
b111 ?
b111 ("
b111 C
1`
b1000 E
b111 f
05
0a
b101011111000000 ]
b111100000001000 \
1'
#24000
0'
#25000
bx j
bx "
bx )
bx >"
bx -
bx x
bx ;"
b0 ,
b0 w
b0 <"
xu
xn
bx m
bx o
b100000001 $
b100000001 .
b100000001 D
b100000001 B"
0=
bx v
bx p
bx s
bx r
xt
bx 8
bx H
bx z
xq
b0 y
b1 3
b1 A
b1 '"
b1000 &
b1000 ;
b1000 @
b1000 ="
b110 C
1c
b111 4
b111 B
b111 k
1:
b0 6
b0 F
b0 i
b0 0
b0 ?
b0 ("
b1001 E
b1000 f
b110 h
b110000000010000 \
b111100000001000 ]
1'
#26000
0'
#27000
b10 3
b10 A
b10 '"
0c
b1001 d
b110 4
b110 B
b110 k
0:
b0 C
0`
0^
b110000000010000 ]
b100000001 \
1'
#28000
0'
#29000
b100001010 $
b100001010 .
b100001010 D
b100001010 B"
b1001 &
b1001 ;
b1001 @
b1001 ="
b1010 d
b1 e
b1010 E
b1001 f
1^
1'
#30000
0'
#31000
b100 m
0u
1n
b100 v
b1111111111111100 p
0t
b110 8
b110 H
b110 z
1q
b0 j
b0 "
b0 )
b0 >"
b0 -
b0 x
b0 ;"
bx ,
bx w
bx <"
b100 o
b0 l
b0 $
b0 .
b0 D
b0 B"
b0 s
b0 r
b100 y
b0 3
b0 A
b0 '"
1+"
0G
1+
b100000 &
b100000 ;
b100000 @
b100000 ="
b0 *
b0 2"
b1011 d
b0 4
b0 B
b0 k
b100 6
b100 F
b100 i
b100 0
b100 ?
b100 ("
b1 /
b1 >
b1 )"
b1 g
1`
b1011 E
b1010 f
15
1a
b100000001 ]
b100001010 \
1'
#32000
0'
#33000
b1 3
b1 A
b1 '"
0+"
1,"
b100001 &
b100001 ;
b100001 @
b100001 ="
b0 e
b10 /
b10 >
b10 )"
0^
b100001010 ]
b0 4"
1'
#34000
0'
#35000
b10100010001000 *
b10100010001000 2"
b10100010001000 $
b10100010001000 .
b10100010001000 D
b10100010001000 B"
b1010 &
b1010 ;
b1010 @
b1010 ="
0,"
1G
0+
b0 g
0`
b0 5"
1'
#36000
0'
#37000
b1000100000000 *
b1000100000000 2"
1<
b1000100000000 $
b1000100000000 .
b1000100000000 D
b1000100000000 B"
b1011 &
b1011 ;
b1011 @
b1011 ="
b1100 d
b10 C
b1100 E
b1011 f
1^
b10100010001000 \
1'
#38000
0'
#39000
b0 9
b0 &"
b0 ,
b0 w
b0 <"
1u
0n
b0 m
b0 o
0<
b100001001 $
b100001001 .
b100001001 D
b100001001 B"
b0 v
b0 p
b0 s
b0 r
0t
b1 8
b1 H
b1 z
0q
b0 y
1*"
b1 e
1+
b1100 &
b1100 ;
b1100 @
b1100 ="
b0 *
b0 2"
b1101 d
b10 4
b10 B
b10 k
1:
b10 6
b10 F
b10 i
b10 0
b10 ?
b10 ("
b0 /
b0 >
b0 )"
b1 C
1`
b1101 E
b1100 f
1[
05
0a
b10100010001000 ]
b1000100000000 \
1'
#40000
0'
#41000
bx ,
bx w
bx <"
0*"
0#
bx *
bx 2"
0u
1n
b100 m
b100 o
0+
1!
b0 $
b0 .
b0 D
b0 B"
02
bx 9
bx &"
b100 v
b1111111111111100 p
b110 8
b110 H
b110 z
1q
b100 y
b0 3
b0 A
b0 '"
b1 %
b1 7
11
b100000 &
b100000 ;
b100000 @
b100000 ="
0G
b0 C
b1110 d
b1 4
b1 B
b1 k
0:
b100 6
b100 F
b100 i
b100 0
b100 ?
b100 ("
0[
1b
b1110 E
b1101 f
b1 g
b100001001 \
b1000100000000 ]
1'
#42000
0'
#43000
1+"
1#
1+
12
0!
b100001 &
b100001 ;
b100001 @
b100001 ="
b0 e
b0 *
b0 2"
b1 3
b1 A
b1 '"
b10 %
b10 7
01
b0 4
b0 B
b0 k
b1 /
b1 >
b1 )"
0^
15
1a
0b
b100001001 ]
1'
#44000
0'
#45000
b10000001001000 *
b10000001001000 2"
b10000001001000 $
b10000001001000 .
b10000001001000 D
b10000001001000 B"
0+"
b1101 &
b1101 ;
b1101 @
b1101 ="
0+
1G
0`
b0 g
1'
#46000
0'
#47000
b1000100001000 *
b1000100001000 2"
1<
b1000100001000 $
b1000100001000 .
b1000100001000 D
b1000100001000 B"
b1110 &
b1110 ;
b1110 @
b1110 ="
b1111 d
b10 C
1^
b1111 E
b1110 f
b10000001001000 \
1'
#48000
0'
#49000
b0 ,
b0 w
b0 <"
0<
b1 m
b1 o
b110000000000100 $
b110000000000100 .
b110000000000100 D
b110000000000100 B"
b1 e
b1 9
b1 &"
b1 v
b1111111111111111 p
b1 y
1*"
b1 *
b1 2"
b1111 &
b1111 ;
b1111 @
b1111 ="
1+
b1 C
b10000 d
b10 4
b10 B
b10 k
b1 6
b1 F
b1 i
b1 0
b1 ?
b1 ("
b0 /
b0 >
b0 )"
1[
05
0a
b10000 E
b1111 f
1`
b1000100001000 \
b10000001001000 ]
1'
#50000
0'
#51000
b10000 s
b1 j
b1 "
b1 )
b1 >"
b1 -
b1 x
b1 ;"
bx ,
bx w
bx <"
0#
0*"
bx *
bx 2"
b101 m
b101 o
02
b0 $
b0 .
b0 D
b0 B"
0+
1!
bx 9
bx &"
b101 v
b1111111111111101 p
b100 y
b0 e
0G
b100001 &
b100001 ;
b100001 @
b100001 ="
b0 3
b0 A
b0 '"
b1 %
b1 7
11
b10001 d
b1 4
b1 B
b1 k
b100 6
b100 F
b100 i
b100 0
b100 ?
b100 ("
b110 C
b1 g
b10001 E
b10000 f
0[
1b
b1 3"
b1000100001000 ]
b110000000000100 \
1'
#52000
0'
#53000
b1 ,
b1 w
b1 <"
b100000000 $
b100000000 .
b100000000 D
b100000000 B"
1#
b1 m
b1 o
0!
12
b1 v
b1 p
b1 s
b1 r
1t
b1010 8
b1010 H
b1010 z
0q
b0 y
b10000 &
b10000 ;
b10000 @
b10000 ="
b10 %
b10 7
01
1G
1c
b100 d
b110 4
b110 B
b110 k
b0 6
b0 F
b0 i
b0 0
b0 ?
b0 ("
b100 /
b100 >
b100 )"
0b
0^
b0 g
b110000000000100 ]
1'
#54000
0'
